open_mastr/__init__.py
open_mastr/mastr.py
open_mastr/soap_api/__init__.py
open_mastr/soap_api/download.py
open_mastr/soap_api/mirror.py
open_mastr/soap_api/parallel.py
open_mastr/soap_api/utils.py
open_mastr/soap_api/metadata/LICENSE
open_mastr/soap_api/metadata/__init__.py
open_mastr/soap_api/metadata/create.py
open_mastr/soap_api/metadata/description.py
open_mastr/soap_api/metadata/mastr_datapackage.json
open_mastr/soap_api/metadata/archiv/mastr_biomass_oem140.json
open_mastr/soap_api/metadata/archiv/mastr_datapackage_oem140.json
open_mastr/soap_api/metadata/archiv/mastr_hydro_oem140.json
open_mastr/soap_api/metadata/archiv/mastr_nuclear_oem140.json
open_mastr/soap_api/metadata/archiv/mastr_solar_oem140.json
open_mastr/soap_api/metadata/archiv/mastr_storage_oem140.json
open_mastr/soap_api/metadata/archiv/mastr_wind_oem140.json
open_mastr/utils/__init__.py
open_mastr/utils/config.py
open_mastr/utils/constants.py
open_mastr/utils/credentials.py
open_mastr/utils/docs.py
open_mastr/utils/helpers.py
open_mastr/utils/orm.py
open_mastr/utils/unzip_http.py
open_mastr/utils/config/logging.yml
open_mastr/xml_download/colums_to_replace.py
open_mastr/xml_download/utils_cleansing_bulk.py
open_mastr/xml_download/utils_download_bulk.py
open_mastr/xml_download/utils_write_to_database.py
open_mastr-0.16.1.dist-info/licenses/LICENSE.md
open_mastr-0.16.1.dist-info/METADATA
open_mastr-0.16.1.dist-info/WHEEL
open_mastr-0.16.1.dist-info/top_level.txt
open_mastr-0.16.1.dist-info/RECORD
