Metadata-Version: 2.4
Name: open_mastr
Version: 0.16.1
Summary: A package that provides an interface for downloading and processing the data of the Marktstammdatenregister (MaStR)
Author: Hülk Ludwig, Pleßmann Guido, Muschner Christoph, Kotthoff Florian, Tepe Deniz, Amme Jonathan, Open Energy Family
Maintainer: Florian Kotthoff, Christoph Muschner
Maintainer-email: Jonathan Amme <jonathan.amme@rl-institut.de>, Ludwig Hülk <datenzentrum@rl-institut.de>
License: AGPL-3.0-or-later
Project-URL: Homepage, https://github.com/OpenEnergyPlatform/open-MaStR
Project-URL: Documentation, https://open-mastr.readthedocs.io/
Project-URL: Repository, https://github.com/OpenEnergyPlatform/open-MaStR
Project-URL: Bug Tracker, https://github.com/OpenEnergyPlatform/open-MaStR/issues
Project-URL: Changelog, https://github.com/OpenEnergyPlatform/open-MaStR/blob/production/CHANGELOG.md
Keywords: Markstammdatenregister,Energy,Dataset,Solar,Wind,Energy-data,OEP,OpenEnergyFamily
Classifier: License :: OSI Approved :: GNU Affero General Public License v3 or later (AGPLv3+)
Classifier: Development Status :: 4 - Beta
Classifier: Intended Audience :: Science/Research
Classifier: Topic :: Scientific/Engineering
Classifier: Topic :: Scientific/Engineering :: GIS
Requires-Python: <4,>=3.9
License-File: LICENSE.md
Requires-Dist: pandas>=2.2.2
Requires-Dist: numpy
Requires-Dist: sqlalchemy>=2.0
Requires-Dist: psycopg2-binary
Requires-Dist: zeep
Requires-Dist: tqdm
Requires-Dist: requests
Requires-Dist: keyring
Requires-Dist: pyyaml
Requires-Dist: xmltodict
Provides-Extra: dev
Requires-Dist: flake8; extra == "dev"
Requires-Dist: pylint; extra == "dev"
Requires-Dist: pytest; extra == "dev"
Requires-Dist: pytest-dependency; extra == "dev"
Requires-Dist: xmltodict; extra == "dev"
Requires-Dist: pre-commit; extra == "dev"
Requires-Dist: bump2version; extra == "dev"
Requires-Dist: mkdocstrings[python]; extra == "dev"
Requires-Dist: mkdocs-material; extra == "dev"
Requires-Dist: mkdocs-include-markdown-plugin; extra == "dev"
Requires-Dist: black; extra == "dev"
Dynamic: license-file
